{"cameraMode":{"drawMode":0,"name":"Shaded","section":"Shading Mode"},"sceneLighting":false,"audioPlay":false,"sceneViewState":{"showFog":true,"showMaterialUpdate":false,"showSkybox":true,"showFlares":true,"showImageEffects":true,"showParticleSystems":true,"showVisualEffectGraphs":true,"m_FxEnabled":true},"in2DMode":false,"pivot":{"x":-298.00372314453127,"y":402.2044982910156,"z":-32.578369140625},"rotation":{"x":-0.4279710650444031,"y":-0.11016850173473358,"z":0.05264298617839813,"w":-0.8955262899398804},"size":139.8036346435547,"orthographic":false}